setup.py
MySerializatorOfXmlAndJson.egg-info/PKG-INFO
MySerializatorOfXmlAndJson.egg-info/SOURCES.txt
MySerializatorOfXmlAndJson.egg-info/dependency_links.txt
MySerializatorOfXmlAndJson.egg-info/requires.txt
MySerializatorOfXmlAndJson.egg-info/top_level.txt
serializers/__init__.py
serializers/factory.py