Metadata-Version: 2.1
Name: MySerializatorOfXmlAndJson
Version: 0.1.1
Summary: Library for serialization
Author: Ilya Danilenko
Author-email: ilyadanilenko2003@mail.ru
Classifier: Intended Audience :: Developers
Classifier: Programming Language :: Python :: 3.10
Classifier: Operating System :: OS Independent
